Metadata-Version: 2.4
Name: hack4u_001
Version: 0.5.0
Summary: Una biblioteca para consultar cursos de hack4u
Home-page: https://hack4u.io
Author: FinalizadorX
Dynamic: author
Dynamic: description
Dynamic: description-content-type
Dynamic: home-page
Dynamic: summary
